src/__main__.py
src/config.py
src/server.py
src/test.py
src/clients/asr_client.py
src/clients/base_client.py
src/clients/tts_client.py
src/tools/asr_tool.py
src/tools/base.py
src/tools/manager.py
src/tools/tts_tool.py
src/utils/utils.py
mt_speech_mcp_server-0.0.2.dist-info/METADATA
mt_speech_mcp_server-0.0.2.dist-info/WHEEL
mt_speech_mcp_server-0.0.2.dist-info/entry_points.txt
mt_speech_mcp_server-0.0.2.dist-info/RECORD
