Metadata-Version: 2.4
Name: mt-speech-mcp-server
Version: 0.0.2
Summary: 美团语音 MCP服务器 - 提供文本转语音和语音识别等语音功能
Author: lifeilong04
Requires-Python: >=3.10
Requires-Dist: httpx>=0.25.0
Requires-Dist: librosa>=0.10.0
Requires-Dist: mcp>=1.7.1
Requires-Dist: mutagen>=1.47.0
Requires-Dist: pydantic>=2.0.0
Requires-Dist: pydub>=0.25.0
Requires-Dist: soundfile>=0.12.0
